holopazaak/__init__.py
holopazaak/__main__.py
holopazaak/app.py
holopazaak/config.py
holopazaak/main_app.py
holopazaak/main_init.py
holopazaak/main_settings.py
holopazaak/ai/__init__.py
holopazaak/ai/bot.py
holopazaak/ai/strategies.py
holopazaak/audio/__init__.py
holopazaak/audio/sounds.py
holopazaak/data/__init__.py
holopazaak/data/opponents.py
holopazaak/game/__init__.py
holopazaak/game/card.py
holopazaak/game/engine.py
holopazaak/game/player.py
holopazaak/network/__init__.py
holopazaak/network/client.py
holopazaak/network/protocol.py
holopazaak/network/server.py
holopazaak/ui/__init__.py
holopazaak/ui/game_window.py
holopazaak/ui/help_dialog.py
holopazaak/ui/mainwindow.py
holopazaak/ui/opponent_dialog.py
holopazaak/ui/sidedeck_dialog.py
holopazaak/ui/sound.py
holopazaak/ui/styles.py
holopazaak/ui/widgets.py
holopazaak-2.0.0.dist-info/METADATA
holopazaak-2.0.0.dist-info/WHEEL
holopazaak-2.0.0.dist-info/entry_points.txt
holopazaak-2.0.0.dist-info/top_level.txt
holopazaak-2.0.0.dist-info/RECORD
